sitemap_range/__init__.py
sitemap_range/sitemap_range.py
sitemap_range_fetch-0.9.6.data/scripts/sitemap_fetch.py
sitemap_range_fetch-0.9.6.dist-info/LICENSE
sitemap_range_fetch-0.9.6.dist-info/METADATA
sitemap_range_fetch-0.9.6.dist-info/WHEEL
sitemap_range_fetch-0.9.6.dist-info/top_level.txt
sitemap_range_fetch-0.9.6.dist-info/RECORD
