Metadata-Version: 2.1
Name: sitemap-range-fetch
Version: 0.9.6
Summary: Sitemap scraper for news article selection within a certain time range
Home-page: https://blog.garage-coding.com/
Author: Stefan Corneliu Petrea
Author-email: stefan@garage-coding.com
License: UNKNOWN
Platform: UNKNOWN
Classifier: Programming Language :: Python :: 3
Classifier: License :: OSI Approved :: MIT License
Classifier: Operating System :: OS Independent
Requires-Python: >=3.5
Requires-Dist: lxml (>=4.3.2)
Requires-Dist: requests (>=2.21.0)
Requires-Dist: beautifulsoup4 (>=4.9.3)
